crm_events/__init__.py
crm_events/admin.py
crm_events/apps.py
crm_events/models.py
crm_events/tests.py
crm_events/utils.py
crm_events/views.py
crm_events/crms/__init__.py
crm_events/crms/base_service.py
crm_events/crms/clickup/__init__.py
crm_events/crms/clickup/exceptions.py
crm_events/crms/hubfy/__init__.py
crm_events/crms/klaviyo/__init__.py
crm_events/crms/pipedrive/__init__.py
crm_events/crms/pipedrive/exceptions.py
crm_events/migrations/__init__.py
django_crm_events-1.0.16.dist-info/METADATA
django_crm_events-1.0.16.dist-info/WHEEL
django_crm_events-1.0.16.dist-info/top_level.txt
django_crm_events-1.0.16.dist-info/RECORD
